pynversify/__init__.py
pynversify/pynversify.py
pynversify-1.0.2.dist-info/METADATA
pynversify-1.0.2.dist-info/WHEEL
pynversify-1.0.2.dist-info/top_level.txt
pynversify-1.0.2.dist-info/RECORD
