Metadata-Version: 2.1
Name: pynversify
Version: 1.0.2
Summary: Dependency Injection Container inspired by Inversify for Python
Home-page: https://github.com/fdorantesm/pynversify
Author: Fernando Dorantes
Author-email: fernando@dorant.es
Classifier: Programming Language :: Python :: 3
Classifier: License :: OSI Approved :: MIT License
Classifier: Operating System :: OS Independent
Requires-Python: >=3.6
